{
    "data": [
        {
            "Name": "Apollo tyres",
            "added_on": "2015-01-02T16:50:17+05:30",
            "last_conversation": "they mainly require the price in reports , which are not available . Hence not interested ",
            "local_id": 3400,
            "phone_no": null,
            "user_id": "nitisha70701"
        },
        {
            "Name": "sabibrahi traders",
            "added_on": "2015-01-02T16:51:54+05:30",
            "last_conversation": null,
            "local_id": 3401,
            "phone_no": null,
            "user_id": "bhawna"
        }
    ]
}